c_logger/__init__.py
c_logger/config.py
c_logger/main.py
c_logger-0.0.1.dist-info/LICENSE
c_logger-0.0.1.dist-info/METADATA
c_logger-0.0.1.dist-info/WHEEL
c_logger-0.0.1.dist-info/top_level.txt
c_logger-0.0.1.dist-info/RECORD
