Metadata-Version: 2.1
Name: c-logger
Version: 0.0.1
Summary: Colored log output
Home-page: UNKNOWN
Author: Andrey Bolshakov
Author-email: frost.dat@gmail.com
License: UNKNOWN
Keywords: python,logger
Platform: UNKNOWN
